azure_keyvault_ethereum_py/__init__.py
azure_keyvault_ethereum_py/package.py
azure_keyvault_ethereum_py/package_test.py
azure_keyvault_ethereum_py/utils.py
azure_keyvault_ethereum_py-0.2.dist-info/LICENSE
azure_keyvault_ethereum_py-0.2.dist-info/METADATA
azure_keyvault_ethereum_py-0.2.dist-info/WHEEL
azure_keyvault_ethereum_py-0.2.dist-info/top_level.txt
azure_keyvault_ethereum_py-0.2.dist-info/RECORD
